airless/pdf/__init__.py
airless/pdf/hook/__init__.py
airless/pdf/hook/pdf.py
airless_pdf-0.3.0.dist-info/METADATA
airless_pdf-0.3.0.dist-info/WHEEL
airless_pdf-0.3.0.dist-info/top_level.txt
airless_pdf-0.3.0.dist-info/RECORD
