Metadata-Version: 2.4
Name: airless-pdf
Version: 0.3.0
Summary: Airless package to manipulate pdf
License: MIT License
Project-URL: Homepage, https://github.com/astercapital/airless
Project-URL: Bug Tracker, https://github.com/astercapital/airless/issues
Requires-Python: >=3.9
Requires-Dist: airless-core>=0.2.1
Requires-Dist: pymupdf<2.0.0,>=1.24.10
